{
  "model_version": "credit_model_2024-04-01",
  "timestamp": "2025-10-29 17:40:02",
  "training_window": [
    "2023_08_01",
    "2024_04_01"
  ],
  "hp_params": {
    "subsample": 0.6,
    "reg_lambda": 2,
    "reg_alpha": 1,
    "n_estimators": 50,
    "min_child_weight": 5,
    "max_depth": 3,
    "learning_rate": 0.1,
    "gamma": 0,
    "colsample_bytree": 0.8
  },
  "cv_auc": 0.7966092020914328,
  "results": {
    "train": {
      "auc": 0.8895684934327006,
      "gini": 0.7791369868654012,
      "ks": 0.6174283910459643,
      "f1": 0.54638124362895,
      "accuracy": 0.8458607551091099,
      "precision": 0.8145896656534954,
      "recall": 0.4110429447852761
    },
    "val": {
      "auc": 0.7736818405108892,
      "gini": 0.5473636810217783,
      "ks": 0.47785328311773373,
      "f1": 0.38888888888888895,
      "accuracy": 0.7876447876447876,
      "precision": 0.625,
      "recall": 0.28225806451612906
    },
    "test": {
      "auc": 0.7990639746267502,
      "gini": 0.5981279492535003,
      "ks": 0.45542275856733966,
      "f1": 0.49289099526066354,
      "accuracy": 0.7906066536203522,
      "precision": 0.7222222222222222,
      "recall": 0.37410071942446044
    },
    "oot": {
      "auc": 0.7873918694814217,
      "gini": 0.5747837389628434,
      "ks": 0.48379723006588676,
      "f1": 0.3975903614457832,
      "accuracy": 0.8050682261208577,
      "precision": 0.6,
      "recall": 0.2972972972972973
    }
  },
  "monitoring": {
    "top_features_for_PSI": [
      "Interest_Rate",
      "Outstanding_Debt",
      "Payment_Behaviour_Bad",
      "sum_fe_10_L3M",
      "Delay_from_due_date",
      "Payment_Behaviour_Good",
      "avg_fe_12_L3M",
      "sum_fe_1_L3M",
      "LoanType_Student_Loan",
      "fe_8_LM",
      "Occupation_Low_spent_Medium_value_payments",
      "Num_Credit_Inquiries",
      "avg_fe_10_L3M",
      "fe_3_LM",
      "avg_fe_13_L3M",
      "sum_fe_9_L3M",
      "Changed_Credit_Limit",
      "Credit_Mix_Entrepreneur",
      "sum_fe_5_L3M",
      "avg_fe_5_L3M"
    ],
    "feature_importance_gain": [
      {
        "feature": "Interest_Rate",
        "gain": 39.51460266113281
      },
      {
        "feature": "Outstanding_Debt",
        "gain": 32.58645248413086
      },
      {
        "feature": "Payment_Behaviour_Bad",
        "gain": 29.044471740722656
      },
      {
        "feature": "sum_fe_10_L3M",
        "gain": 20.68016815185547
      },
      {
        "feature": "Delay_from_due_date",
        "gain": 15.30375862121582
      },
      {
        "feature": "Payment_Behaviour_Good",
        "gain": 12.917143821716309
      },
      {
        "feature": "avg_fe_12_L3M",
        "gain": 12.41665267944336
      },
      {
        "feature": "sum_fe_1_L3M",
        "gain": 11.92314338684082
      },
      {
        "feature": "LoanType_Student_Loan",
        "gain": 10.955820083618164
      },
      {
        "feature": "fe_8_LM",
        "gain": 10.69201946258545
      },
      {
        "feature": "Occupation_Low_spent_Medium_value_payments",
        "gain": 10.690305709838867
      },
      {
        "feature": "Num_Credit_Inquiries",
        "gain": 10.558545112609863
      },
      {
        "feature": "avg_fe_10_L3M",
        "gain": 10.533928871154785
      },
      {
        "feature": "fe_3_LM",
        "gain": 10.360209465026855
      },
      {
        "feature": "avg_fe_13_L3M",
        "gain": 10.314770698547363
      },
      {
        "feature": "sum_fe_9_L3M",
        "gain": 9.795378684997559
      },
      {
        "feature": "Changed_Credit_Limit",
        "gain": 9.779983520507812
      },
      {
        "feature": "Credit_Mix_Entrepreneur",
        "gain": 9.770069122314453
      },
      {
        "feature": "sum_fe_5_L3M",
        "gain": 9.676198959350586
      },
      {
        "feature": "avg_fe_5_L3M",
        "gain": 9.664382934570312
      },
      {
        "feature": "avg_fe_20_L3M",
        "gain": 9.37177562713623
      },
      {
        "feature": "avg_fe_2_L3M",
        "gain": 9.370329856872559
      },
      {
        "feature": "Num_Credit_Card",
        "gain": 9.19375991821289
      },
      {
        "feature": "avg_fe_11_L3M",
        "gain": 9.153388977050781
      },
      {
        "feature": "avg_fe_17_L3M",
        "gain": 9.115882873535156
      },
      {
        "feature": "Credit_History_Age_Months",
        "gain": 9.095760345458984
      },
      {
        "feature": "sum_fe_16_L3M",
        "gain": 8.868471145629883
      },
      {
        "feature": "avg_fe_1_L3M",
        "gain": 8.624427795410156
      },
      {
        "feature": "sum_fe_3_L3M",
        "gain": 8.544231414794922
      },
      {
        "feature": "avg_fe_9_L3M",
        "gain": 8.472362518310547
      },
      {
        "feature": "fe_11_LM",
        "gain": 8.392613410949707
      },
      {
        "feature": "avg_fe_8_L3M",
        "gain": 8.379698753356934
      },
      {
        "feature": "fe_17_LM",
        "gain": 8.3690824508667
      },
      {
        "feature": "fe_4_LM",
        "gain": 8.330324172973633
      },
      {
        "feature": "avg_fe_7_L3M",
        "gain": 8.306625366210938
      },
      {
        "feature": "sum_fe_7_L3M",
        "gain": 8.271169662475586
      },
      {
        "feature": "avg_fe_3_L3M",
        "gain": 8.181629180908203
      },
      {
        "feature": "Age",
        "gain": 7.991738796234131
      },
      {
        "feature": "sum_fe_2_L3M",
        "gain": 7.902778148651123
      },
      {
        "feature": "sum_fe_13_L3M",
        "gain": 7.880227088928223
      },
      {
        "feature": "fe_2_LM",
        "gain": 7.845929145812988
      },
      {
        "feature": "fe_1_LM",
        "gain": 7.718421936035156
      },
      {
        "feature": "avg_fe_4_L3M",
        "gain": 7.5088324546813965
      },
      {
        "feature": "Amount_invested_monthly",
        "gain": 7.343744277954102
      },
      {
        "feature": "LoanType_Not_Specified",
        "gain": 7.282907485961914
      },
      {
        "feature": "fe_14_LM",
        "gain": 7.1778459548950195
      },
      {
        "feature": "fe_13_LM",
        "gain": 7.076684951782227
      },
      {
        "feature": "avg_fe_16_L3M",
        "gain": 6.990697383880615
      },
      {
        "feature": "fe_20_LM",
        "gain": 6.9442667961120605
      },
      {
        "feature": "Monthly_Inhand_Salary",
        "gain": 6.728742599487305
      },
      {
        "feature": "sum_fe_8_L3M",
        "gain": 6.718414306640625
      },
      {
        "feature": "sum_fe_4_L3M",
        "gain": 6.685661315917969
      },
      {
        "feature": "fe_6_LM",
        "gain": 6.333551406860352
      },
      {
        "feature": "fe_16_LM",
        "gain": 6.326641082763672
      },
      {
        "feature": "sum_fe_18_L3M",
        "gain": 6.177812576293945
      },
      {
        "feature": "sum_fe_6_L3M",
        "gain": 6.1132354736328125
      },
      {
        "feature": "avg_fe_18_L3M",
        "gain": 5.966469764709473
      },
      {
        "feature": "Monthly_Balance",
        "gain": 5.818510055541992
      },
      {
        "feature": "fe_19_LM",
        "gain": 5.732887268066406
      },
      {
        "feature": "avg_fe_15_L3M",
        "gain": 5.707729816436768
      },
      {
        "feature": "fe_9_LM",
        "gain": 5.64706563949585
      },
      {
        "feature": "fe_10_LM",
        "gain": 5.542112350463867
      },
      {
        "feature": "fe_15_LM",
        "gain": 5.474818706512451
      },
      {
        "feature": "avg_fe_14_L3M",
        "gain": 5.454073429107666
      },
      {
        "feature": "Annual_Income",
        "gain": 5.409788131713867
      },
      {
        "feature": "fe_7_LM",
        "gain": 5.344879150390625
      },
      {
        "feature": "Credit_Utilization_Ratio",
        "gain": 4.69764518737793
      },
      {
        "feature": "fe_18_LM",
        "gain": 4.635805130004883
      },
      {
        "feature": "sum_fe_20_L3M",
        "gain": 4.212754249572754
      },
      {
        "feature": "Num_of_Loan",
        "gain": 4.025713920593262
      },
      {
        "feature": "fe_12_LM",
        "gain": 3.6271142959594727
      },
      {
        "feature": "Num_of_Delayed_Payment",
        "gain": 3.6097278594970703
      },
      {
        "feature": "Occupation_High_spent_Small_value_payments",
        "gain": 3.568756103515625
      },
      {
        "feature": "fe_5_LM",
        "gain": 2.877378463745117
      },
      {
        "feature": "sum_fe_19_L3M",
        "gain": 1.3940342664718628
      }
    ],
    "baseline_feature_stats": {
      "Interest_Rate": {
        "quantiles": [
          4.0,
          7.0,
          9.0,
          11.0,
          13.0,
          16.0,
          19.0,
          23.0,
          30.0
        ]
      },
      "Outstanding_Debt": {
        "quantiles": [
          231.2860046386719,
          462.9160034179688,
          691.1200195312504,
          923.3699829101563,
          1161.4100341796875,
          1332.6679443359376,
          1539.6399902343749,
          2201.0120117187503,
          3073.973974609375
        ]
      },
      "sum_fe_10_L3M": {
        "quantiles": [
          131.0,
          211.20000000000005,
          268.0,
          315.0,
          359.0,
          399.0,
          448.1999999999998,
          508.8000000000002,
          583.4000000000001
        ]
      },
      "Delay_from_due_date": {
        "quantiles": [
          5.0,
          8.0,
          11.0,
          14.0,
          17.0,
          21.0,
          26.0,
          30.0,
          45.0
        ]
      },
      "avg_fe_12_L3M": {
        "quantiles": [
          24.666666666666668,
          50.0,
          68.9333333333334,
          84.33333333333333,
          99.33333333333333,
          114.33333333333333,
          131.0666666666666,
          149.9333333333334,
          175.0
        ]
      },
      "sum_fe_1_L3M": {
        "quantiles": [
          78.0,
          156.0,
          211.0,
          258.0,
          309.0,
          355.0,
          402.0,
          459.8000000000002,
          536.0
        ]
      },
      "LoanType_Student_Loan": {
        "quantiles": [
          0.0,
          0.0,
          0.0,
          0.0,
          0.0,
          0.0,
          1.0,
          1.0,
          1.0
        ]
      },
      "fe_8_LM": {
        "quantiles": [
          -15.0,
          30.0,
          64.0,
          89.0,
          113.0,
          138.0,
          164.0,
          196.0,
          237.0
        ]
      },
      "Num_Credit_Inquiries": {
        "quantiles": [
          2.0,
          3.0,
          4.0,
          5.0,
          6.0,
          7.0,
          9.0,
          11.0,
          12.0
        ]
      },
      "avg_fe_10_L3M": {
        "quantiles": [
          43.666666666666664,
          70.4,
          89.33333333333333,
          105.0,
          119.66666666666667,
          133.0,
          149.39999999999995,
          169.60000000000005,
          194.4666666666667
        ]
      },
      "fe_3_LM": {
        "quantiles": [
          -30.399999999999977,
          15.0,
          46.0,
          75.0,
          104.0,
          130.0,
          157.0,
          191.0,
          238.0
        ]
      },
      "avg_fe_13_L3M": {
        "quantiles": [
          27.533333333333342,
          52.333333333333336,
          70.33333333333333,
          86.66666666666667,
          101.0,
          114.53333333333346,
          130.66666666666666,
          150.0,
          175.0
        ]
      },
      "sum_fe_9_L3M": {
        "quantiles": [
          121.0,
          195.0,
          245.0,
          293.4000000000001,
          341.0,
          388.0,
          434.0,
          489.0,
          570.4000000000001
        ]
      },
      "Changed_Credit_Limit": {
        "quantiles": [
          2.2360000133514406,
          4.32400016784668,
          6.175999832153324,
          7.840000152587891,
          9.220000267028809,
          10.655999755859378,
          12.524000358581539,
          16.030000686645508,
          19.170000076293945
        ]
      },
      "sum_fe_5_L3M": {
        "quantiles": [
          88.0,
          178.0,
          233.80000000000018,
          276.4000000000001,
          315.0,
          363.0,
          411.0,
          463.8000000000002,
          541.0
        ]
      },
      "avg_fe_5_L3M": {
        "quantiles": [
          29.333333333333332,
          59.333333333333336,
          77.9333333333334,
          92.13333333333337,
          105.0,
          121.0,
          137.0,
          154.60000000000005,
          180.33333333333334
        ]
      }
    }
  },
  "data_stats": {
    "rows_train": 2887,
    "rows_test": 511,
    "rows_oot": 513,
    "y_rate_train": 0.226,
    "y_rate_test": 0.272,
    "y_rate_oot": 0.216
  }
}